setup.py
dmgs_distributions/Binomialdistribution.py
dmgs_distributions/Gaussiandistribution.py
dmgs_distributions/Generaldistribution.py
dmgs_distributions/__init__.py
dmgs_distributions.egg-info/PKG-INFO
dmgs_distributions.egg-info/SOURCES.txt
dmgs_distributions.egg-info/dependency_links.txt
dmgs_distributions.egg-info/not-zip-safe
dmgs_distributions.egg-info/top_level.txt