Metadata-Version: 1.0
Name: dmgs-distributions
Version: 0.1
Summary: Gaussian and Binomial distributions
Home-page: UNKNOWN
Author: Daniel Guatibonza
Author-email: UNKNOWN
License: UNKNOWN
Platform: UNKNOWN
